LICENSE.md
MANIFEST.in
README.md
requirements.txt
setup.py
simpledash/__init__.py
simpledash.egg-info/PKG-INFO
simpledash.egg-info/SOURCES.txt
simpledash.egg-info/dependency_links.txt
simpledash.egg-info/requires.txt
simpledash.egg-info/top_level.txt
simpledash/callbacks/__init__.py
simpledash/data/__init__.py
simpledash/data/data_providers.py
simpledash/inspector/__init__.py
simpledash/inspector/accessors.py
simpledash/inspector/component.py
simpledash/inspector/layout.py